GreenPonik_BH1750/BH1750.py
GreenPonik_BH1750/__init__.py
tests/__init__.py
tests/test_BH1750.py
greenponik_bh1750-0.0.7.dist-info/METADATA
greenponik_bh1750-0.0.7.dist-info/WHEEL
greenponik_bh1750-0.0.7.dist-info/top_level.txt
greenponik_bh1750-0.0.7.dist-info/RECORD
