Metadata-Version: 2.1
Name: greenponik-bh1750
Version: 0.0.7
Summary: Read BH1750 through Python3 on raspberry pi
Home-page: https://github.com/GreenPonik/GreenPonik_BH1750
Author: GreenPonik SAS
Author-email: contact@greenponik.com
License: MIT
Project-URL: Source, https://github.com/GreenPonik/GreenPonik_BH1750/
Project-URL: Bug Reports, https://github.com/GreenPonik/            GreenPonik_BH1750/issues
Keywords: GreenPonik hydroponics bh1750     light reader python hardware diy iot raspberry pi
Platform: UNKNOWN
Classifier: Programming Language :: Python :: 3
Classifier: License :: OSI Approved :: MIT License
Classifier: Operating System :: OS Independent
Requires-Python: >=3.6.0
Requires-Dist: adafruit-blinka
Requires-Dist: adafruit-circuitpython-bh1750
Requires-Dist: adafruit-extended-bus
